[
  {
    "lesson": "Code failed to compile: . Always run TypeScript check before marking complete.",
    "category": "typescript",
    "timestamp": "2026-03-15T19:32:05",
    "iteration": 1
  },
  {
    "lesson": "Code failed to compile: . Always run TypeScript check before marking complete.",
    "category": "typescript",
    "timestamp": "2026-03-15T19:36:12",
    "iteration": 2
  },
  {
    "lesson": "Code failed to compile: . Always run TypeScript check before marking complete.",
    "category": "typescript",
    "timestamp": "2026-03-15T19:40:35",
    "iteration": 3
  },
  {
    "lesson": "Code failed to compile: . Always run TypeScript check before marking complete.",
    "category": "typescript",
    "timestamp": "2026-03-15T19:44:50",
    "iteration": 4
  },
  {
    "lesson": "Code failed to compile: . Always run TypeScript check before marking complete.",
    "category": "typescript",
    "timestamp": "2026-03-15T19:49:32",
    "iteration": 5
  },
  {
    "lesson": "Code failed to compile: . Always run TypeScript check before marking complete.",
    "category": "typescript",
    "timestamp": "2026-03-15T19:53:35",
    "iteration": 7
  }
]